csvdeploy/__init__.py
csvdeploy/__main__.py
csvdeploy/common.py
csvdeploy/render.py
csvdeploy-0.1.data/data/base.html
csvdeploy-0.1.data/data/datatable.html
csvdeploy-0.1.data/data/index.html
csvdeploy-0.1.data/data/main.css
csvdeploy-0.1.data/data/sql.html
csvdeploy-0.1.data/data/demo_data/langgenera/langgenera.config.json
csvdeploy-0.1.data/data/demo_data/langgenera/langgenera.tsv
csvdeploy-0.1.data/data/docs/README.md
csvdeploy-0.1.dist-info/AUTHORS.md
csvdeploy-0.1.dist-info/LICENSE
csvdeploy-0.1.dist-info/METADATA
csvdeploy-0.1.dist-info/WHEEL
csvdeploy-0.1.dist-info/entry_points.txt
csvdeploy-0.1.dist-info/top_level.txt
csvdeploy-0.1.dist-info/RECORD
