Metadata-Version: 2.1
Name: csvdeploy
Version: 0.1
Summary: A package for deploying tabular data files as static websites
Home-page: https://github.com/tresoldi/csvdeploy
Author: Tiago Tresoldi
Author-email: tiago.tresoldi@lingfil.uu.se
License: GNU GPL3
Keywords: csv,tsv,tabular data,static website,deployment
Platform: UNKNOWN
Classifier: License :: OSI Approved :: MIT License
Classifier: Operating System :: OS Independent
Classifier: Programming Language :: Python :: 3
Classifier: Topic :: Software Development :: Libraries
Requires-Dist: jinja2
Requires-Dist: tabulate
Requires-Dist: unidecode
Requires-Dist: Markdown
